spyder_okvim/__init__.py
spyder_okvim/conftest.py
spyder_okvim/executor/__init__.py
spyder_okvim/executor/decorators.py
spyder_okvim/executor/executor_base.py
spyder_okvim/executor/executor_colon.py
spyder_okvim/executor/executor_easymotion.py
spyder_okvim/executor/executor_leader.py
spyder_okvim/executor/executor_normal.py
spyder_okvim/executor/executor_sub.py
spyder_okvim/executor/executor_surround.py
spyder_okvim/executor/executor_visual.py
spyder_okvim/executor/executor_vline.py
spyder_okvim/executor/mixins.py
spyder_okvim/executor/tests/test_colon.py
spyder_okvim/executor/tests/test_easymotion.py
spyder_okvim/executor/tests/test_leader_key.py
spyder_okvim/executor/tests/test_normal.py
spyder_okvim/executor/tests/test_surround.py
spyder_okvim/executor/tests/test_visual.py
spyder_okvim/executor/tests/test_vline.py
spyder_okvim/spyder/__init__.py
spyder_okvim/spyder/api.py
spyder_okvim/spyder/config.py
spyder_okvim/spyder/confpage.py
spyder_okvim/spyder/plugin.py
spyder_okvim/spyder/vim_widgets.py
spyder_okvim/spyder/tests/test_bookmarks.py
spyder_okvim/spyder/tests/test_widgets.py
spyder_okvim/utils/__init__.py
spyder_okvim/utils/action_helpers.py
spyder_okvim/utils/bookmark_manager.py
spyder_okvim/utils/cell_helpers.py
spyder_okvim/utils/easymotion.py
spyder_okvim/utils/file_search.py
spyder_okvim/utils/jump_dialog.py
spyder_okvim/utils/jump_list.py
spyder_okvim/utils/list_dialog.py
spyder_okvim/utils/mark_dialog.py
spyder_okvim/utils/motion.py
spyder_okvim/utils/motion_helpers.py
spyder_okvim/utils/search_helpers.py
spyder_okvim/utils/testing_env.py
spyder_okvim/utils/text_constants.py
spyder_okvim/utils/tests/test_cell_helpers.py
spyder_okvim/utils/tests/test_dialog_widgets.py
spyder_okvim/utils/tests/test_file_search.py
spyder_okvim/utils/tests/test_jump_list.py
spyder_okvim/vim/__init__.py
spyder_okvim/vim/cursor.py
spyder_okvim/vim/label.py
spyder_okvim/vim/macro.py
spyder_okvim/vim/search.py
spyder_okvim/vim/state.py
spyder_okvim/vim/status.py
spyder_okvim-0.10.6.dist-info/licenses/LICENSE
spyder_okvim-0.10.6.dist-info/METADATA
spyder_okvim-0.10.6.dist-info/WHEEL
spyder_okvim-0.10.6.dist-info/entry_points.txt
spyder_okvim-0.10.6.dist-info/top_level.txt
spyder_okvim-0.10.6.dist-info/RECORD
