Metadata-Version: 2.4
Name: spyder-okvim
Version: 0.10.6
Summary: Spyder Vim plugin
Author-email: ok97465 <ok97465@kakao.com>
License-Expression: MIT
Project-URL: Homepage, https://github.com/ok97465/spyder_okvim
Project-URL: Source, https://github.com/ok97465/spyder_okvim
Project-URL: Bug Tracker, https://github.com/ok97465/spyder_okvim/issues
Classifier: Operating System :: MacOS
Classifier: Operating System :: Microsoft :: Windows
Classifier: Operating System :: POSIX :: Linux
Classifier: Programming Language :: Python :: 3
Classifier: Development Status :: 5 - Production/Stable
Classifier: Intended Audience :: Education
Classifier: Intended Audience :: Science/Research
Classifier: Intended Audience :: Developers
Classifier: Topic :: Scientific/Engineering
Requires-Python: >=3.9
License-File: LICENSE
Requires-Dist: spyder>=6.1.0
Requires-Dist: qtpy
Dynamic: license-file
